odoo/addons/l10n_br_account_payment_brcobranca/README.rst
odoo/addons/l10n_br_account_payment_brcobranca/__init__.py
odoo/addons/l10n_br_account_payment_brcobranca/__manifest__.py
odoo/addons/l10n_br_account_payment_brcobranca/constants/br_cobranca.py
odoo/addons/l10n_br_account_payment_brcobranca/demo/account_invoice_demo.xml
odoo/addons/l10n_br_account_payment_brcobranca/demo/account_journal_demo.xml
odoo/addons/l10n_br_account_payment_brcobranca/i18n/l10n_br_account_payment_brcobranca.pot
odoo/addons/l10n_br_account_payment_brcobranca/models/__init__.py
odoo/addons/l10n_br_account_payment_brcobranca/models/account_invoice.py
odoo/addons/l10n_br_account_payment_brcobranca/models/account_journal.py
odoo/addons/l10n_br_account_payment_brcobranca/models/account_move_line.py
odoo/addons/l10n_br_account_payment_brcobranca/models/account_payment_order.py
odoo/addons/l10n_br_account_payment_brcobranca/models/bank_payment_line.py
odoo/addons/l10n_br_account_payment_brcobranca/parser/__init__.py
odoo/addons/l10n_br_account_payment_brcobranca/parser/cnab_file_parser.py
odoo/addons/l10n_br_account_payment_brcobranca/readme/CONFIGURE.rst
odoo/addons/l10n_br_account_payment_brcobranca/readme/CONTRIBUTORS.rst
odoo/addons/l10n_br_account_payment_brcobranca/readme/CREDITS.rst
odoo/addons/l10n_br_account_payment_brcobranca/readme/DESCRIPTION.rst
odoo/addons/l10n_br_account_payment_brcobranca/readme/HISTORY.rst
odoo/addons/l10n_br_account_payment_brcobranca/readme/INSTALL.rst
odoo/addons/l10n_br_account_payment_brcobranca/readme/ROADMAP.rst
odoo/addons/l10n_br_account_payment_brcobranca/readme/USAGE.rst
odoo/addons/l10n_br_account_payment_brcobranca/security/ir.model.access.csv
odoo/addons/l10n_br_account_payment_brcobranca/static/description/icon.png
odoo/addons/l10n_br_account_payment_brcobranca/static/description/index.html
odoo/addons/l10n_br_account_payment_brcobranca/tests/__init__.py
odoo/addons/l10n_br_account_payment_brcobranca/tests/test_payment_order.py
odoo12_addon_l10n_br_account_payment_brcobranca-12.0.4.1.2.dist-info/METADATA
odoo12_addon_l10n_br_account_payment_brcobranca-12.0.4.1.2.dist-info/WHEEL
odoo12_addon_l10n_br_account_payment_brcobranca-12.0.4.1.2.dist-info/top_level.txt
odoo12_addon_l10n_br_account_payment_brcobranca-12.0.4.1.2.dist-info/RECORD
